LICENSE.txt
README.md
setup.py
rocket_lamia/__init__.py
rocket_lamia/rocket.py
rocket_lamia.egg-info/PKG-INFO
rocket_lamia.egg-info/SOURCES.txt
rocket_lamia.egg-info/dependency_links.txt
rocket_lamia.egg-info/requires.txt
rocket_lamia.egg-info/top_level.txt