Metadata-Version: 2.1
Name: rocket_lamia
Version: 1.0.0
Summary: An awesome package that does something
Home-page: http://pypi.python.org/pypi/rocket_lamia/
Author: lamia
Author-email: l.abdelmalek@esi-sba.dz
License: LICENSE.txt
License-File: LICENSE.txt
Requires-Dist: rocket_lamia
